src/mux_n.v
module mux_n
    #(
        parameter N = 8   // default = 8
    )
    (
        input  wire [N-1:0] a,   
        input  wire [N-1:0] b,     
        input  wire  sel,  
        output reg  [N-1:0] y     
    );

    always @(*) begin
        case (sel)
            1'b0 : y = a;
            1'b1 : y = b;
            default : y = {N{1'bx}};
        endcase
    end

endmodule

testbench/mux_n_tb.v
`timescale 1ns/1ps

module mux_n_tb;

    parameter N = 8;

    reg  [N-1:0] a, b;
    reg          sel;
    wire [N-1:0] y;

    integer errors = 0;

    // Instantiate the Device Under Test (DUT)
    mux_n #(.N(N)) dut (
        .a   (a),
        .b   (b),
        .sel (sel),
        .y   (y)
    );

    // Dump waveform for GTKWave
    initial begin
        $dumpfile("mux_n_tb.vcd");
        $dumpvars(0, mux_n_tb);
    end

    // Stimulus
    initial begin
        $display("=========================================================");
        $display(" time |   a(hex) |   b(hex) | sel |   y(hex) | expected | result");
        $display("=========================================================");

        a = 8'h00; b = 8'h00; sel = 0; #10; check();
        a = 8'hAA; b = 8'h55; sel = 0; #10; check();
        a = 8'hAA; b = 8'h55; sel = 1; #10; check();
        a = 8'hFF; b = 8'h0F; sel = 0; #10; check();
        a = 8'hFF; b = 8'h0F; sel = 1; #10; check();
        a = 8'h3C; b = 8'hC3; sel = 0; #10; check();
        a = 8'h3C; b = 8'hC3; sel = 1; #10; check();

        $display("=========================================================");
        if (errors == 0)
            $display(" ALL TEST CASES PASSED");
        else
            $display(" %0d TEST CASE(S) FAILED", errors);
        $display("=========================================================");

        #10 $finish;
    end

    task check;
        reg [N-1:0] expected;
        begin
            expected = sel ? b : a;
            $display(" %4t |   %h    |   %h    |  %b  |   %h    |   %h    |  %s",
                       $time, a, b, sel, y, expected,
                       (y === expected) ? "PASS" : "FAIL");
            if (y !== expected) errors = errors + 1;
        end
    endtask

endmodule

mux_n_tb.vcd
$date
	Sun Jun 28 20:52:29 2026
$end
$version
	Icarus Verilog
$end
$timescale
	1ps
$end
$scope module mux_n_tb $end
$var wire 8 ! y [7:0] $end
$var reg 8 " a [7:0] $end
$var reg 8 # b [7:0] $end
$var reg 1 $ sel $end
$var integer 32 % errors [31:0] $end
$scope module dut $end
$var wire 8 & a [7:0] $end
$var wire 8 ' b [7:0] $end
$var wire 1 $ sel $end
$var reg 8 ( y [7:0] $end
$upscope $end
$scope task check $end
$var reg 8 ) expected [7:0] $end
$upscope $end
$upscope $end
$enddefinitions $end
#0
$dumpvars
bx )
b0 (
b0 '
b0 &
b0 %
0$
b0 #
b0 "
b0 !
$end
#10000
b10101010 !
b10101010 (
b1010101 #
b1010101 '
b10101010 "
b10101010 &
b0 )
#20000
b1010101 !
b1010101 (
1$
b10101010 )
#30000
b11111111 !
b11111111 (
0$
b1111 #
b1111 '
b11111111 "
b11111111 &
b1010101 )
#40000
b1111 !
b1111 (
1$
b11111111 )
#50000
b111100 !
b111100 (
0$
b11000011 #
b11000011 '
b111100 "
b111100 &
b1111 )
#60000
b11000011 !
b11000011 (
1$
b111100 )
#70000
b11000011 )
